{
  "ui": {
    "closeBtnAriaLabel": "Закрити",
    "copyBtnLabel": {
      "default": "Скопіювати",
      "active": "Скопійовано"
    }
  },
  "paymentView": {
    "heading": "Реквізити для благодійного внеску",
    "details": [
      {
        "label": "Найменування отримувача",
        "value": "Благодійна організація «Благодійний фонд «Волонтерське об’єднання «Веста»"
      },
      {
        "label": "ЄДРПОУ",
        "value": "42399807"
      },
      {
        "label": "Рахунок отримувача",
        "value": "UA643052990000026004046244539"
      },
      {
        "label": "Найменування банку",
        "value": "АТ КБ «ПРИВАТБАНК»"
      },
      {
        "label": "Автоматичний коментар",
        "value": "Благодійний внесок"
      }
    ]
  }
}
